EasyTuya/TuyaAPI.py
EasyTuya/__init__.py
EasyTuya/devices/Lights.py
EasyTuya/devices/__init__.py
EasyTuya-0.1.371.dist-info/METADATA
EasyTuya-0.1.371.dist-info/WHEEL
EasyTuya-0.1.371.dist-info/license.txt
EasyTuya-0.1.371.dist-info/top_level.txt
EasyTuya-0.1.371.dist-info/RECORD
